kitoken-0.10.1.dist-info/METADATA
kitoken-0.10.1.dist-info/WHEEL
kitoken.pyi
kitoken/__init__.py
kitoken/__init__.pyi
kitoken/py.typed
kitoken/kitoken.abi3.so
kitoken-0.10.1.dist-info/RECORD
