Metadata-Version: 2.3
Name: kitoken
Version: 0.10.1
Classifier: Programming Language :: Rust
Classifier: Programming Language :: Python :: Implementation :: CPython
Classifier: Programming Language :: Python :: Implementation :: PyPy
Classifier: Operating System :: Microsoft :: Windows
Classifier: Operating System :: POSIX :: Linux
Classifier: Operating System :: MacOS :: MacOS X
Classifier: Environment :: Console
Classifier: Topic :: File Formats
Classifier: Topic :: Text Processing :: Linguistic
Classifier: Topic :: Scientific/Engineering :: Artificial Intelligence
Classifier: Topic :: Software Development :: Libraries :: Python Modules
Classifier: Intended Audience :: Developers
Classifier: Intended Audience :: Science/Research
Classifier: Intended Audience :: End Users/Desktop
Classifier: License :: OSI Approved :: BSD License
Classifier: Typing :: Typed
Summary: Fast and versatile tokenizer for language models, supporting BPE, Unigram and WordPiece tokenization
Keywords: tokenizer,nlp,bpe,unigram,wordpiece
Author-email: Christian Sdunek <me@systemcluster.me>
License: BSD-2-Clause
Requires-Python: >=3.10
Project-URL: Homepage, https://kitoken.dev
Project-URL: Repository, https://github.com/Systemcluster/kitoken
